{
    "version": "1.20.0",
    "description": "A cross-platform terminal workspace for remote development and AI agents, powered by libghostty-vt",
    "homepage": "https://github.com/xuzhougeng/wispterm",
    "license": "MIT",
    "url": "https://github.com/xuzhougeng/wispterm/releases/download/v1.20.0/wispterm-windows-portable-v1.20.0.zip",
    "hash": "d1a970d90e76ffa264ee5e338200388083c8a6c6cb231648df3d2bdf6457f1c4",
    "bin": [
        "wispterm.exe",
        "wispterm-ssh-askpass.exe"
    ],
    "shortcuts": [
        [
            "wispterm.exe",
            "WispTerm"
        ]
    ],
    "checkver": "github",
    "autoupdate": {
        "url": "https://github.com/xuzhougeng/wispterm/releases/download/v$version/wispterm-windows-portable-v$version.zip"
    }
}
